braille_radio/__init__.py
braille_radio/config.py
braille_radio/gui.py
braille_radio/indexing.py
braille_radio/radiobrowse.py
braille_radio-0.1.3.dist-info/entry_points.txt
braille_radio-0.1.3.dist-info/WHEEL
braille_radio-0.1.3.dist-info/METADATA
braille_radio-0.1.3.dist-info/RECORD
