Metadata-Version: 2.1
Name: braille-radio
Version: 0.1.3
Summary: A minimal internet radio optimized for braille users
Home-page: https://github.com/Inqbus/braille_radio.git
License: MIT
Keywords: braille,internet radio,radio
Author: volker
Author-email: volker.jaenisch@inqbus.de
Requires-Python: >=3.7,<4.0
Classifier: Environment :: Console
Classifier: License :: OSI Approved :: MIT License
Classifier: Operating System :: OS Independent
Classifier: Programming Language :: Python :: 3
Classifier: Programming Language :: Python :: 3.7
Classifier: Programming Language :: Python :: 3.8
Classifier: Programming Language :: Python :: 3.9
Classifier: Topic :: Software Development :: Libraries :: Python Modules
Requires-Dist: Whoosh (>=2.7.4,<3.0.0)
Requires-Dist: addict (>=2.4.0,<3.0.0)
Requires-Dist: objsize (>=0.3.3,<0.4.0)
Requires-Dist: progressbar (>=2.5,<3.0)
Requires-Dist: python-vlc (>=3.0.11115,<4.0.0)
Requires-Dist: xarray (>=0.16.2,<0.17.0)
Project-URL: Repository, https://github.com/Inqbus/braille_radio.git
